pyxarf/__init__.py
pyxarf/exceptions.py
pyxarf/xarf.py
pyxarf-0.1.0.data/scripts/xarfutil.py
xarfmail/__init__.py
xarfmail/xarfmail.py
pyxarf-0.1.0.dist-info/LICENSE.txt
pyxarf-0.1.0.dist-info/METADATA
pyxarf-0.1.0.dist-info/WHEEL
pyxarf-0.1.0.dist-info/top_level.txt
pyxarf-0.1.0.dist-info/RECORD
