Metadata-Version: 2.1
Name: pyxarf
Version: 0.1.0
Summary: pyxarf - easy x-arf report generation
Home-page: http://xarf.org/
Author: abusix
Author-email: info@abusix.com
License: Apache Software License
Project-URL: Source, https://github.com/xarf/python-xarf
Project-URL: Company, https://www.abusix.com/
Keywords: keyword,search,purepython,aho-corasick,ahocorasick,abusix
Platform: UNKNOWN
Classifier: Development Status :: 4 - Beta
Classifier: Environment :: Console
Classifier: Intended Audience :: Customer Service
Classifier: Intended Audience :: System Administrators
Classifier: Operating System :: MacOS :: MacOS X
Classifier: Operating System :: POSIX
Classifier: Programming Language :: Python :: 2
Classifier: Programming Language :: Python :: 2.7
Classifier: Programming Language :: Python :: 3
Classifier: Programming Language :: Python :: 3.3
Classifier: Programming Language :: Python :: 3.4
Classifier: Programming Language :: Python :: 3.5
Classifier: Programming Language :: Python :: 3.6
Classifier: Programming Language :: Python :: 3.7
Classifier: Topic :: Security
Classifier: License :: OSI Approved :: Apache Software License
Requires-Python: >=2.7
Requires-Dist: jsonschema (>=3.0.2)
Requires-Dist: PyYAML (>=5.1.2)
Requires-Dist: dnspython (>=1.16.0)
Requires-Dist: querycontacts (>=1.1.1)
Requires-Dist: requests (>=2.22.0)
